styles/__init__.py
styles/styles.py
circuitpython_styles-0.7.1.dist-info/LICENSE
circuitpython_styles-0.7.1.dist-info/METADATA
circuitpython_styles-0.7.1.dist-info/WHEEL
circuitpython_styles-0.7.1.dist-info/top_level.txt
circuitpython_styles-0.7.1.dist-info/RECORD
