Metadata-Version: 2.1
Name: circuitpython-styles
Version: 0.7.1
Summary: Dynamic style helper for CircuitPython graphical elements
Home-page: https://github.com/jposada202020/CircuitPython_styles.git
Author: Jose David M.
Author-email: "Jose D. Montoya" <styles@mailmeto.mozmail.com>
License: MIT
Project-URL: Homepage, https://github.com/jposada202020/CircuitPython_styles.git
Keywords: hardware,micropython,circuitpython,graphic,styles,widget,displayio,color,widget,themes
Classifier: Intended Audience :: Developers
Classifier: Topic :: Software Development :: Libraries
Classifier: Topic :: Software Development :: Embedded Systems
Classifier: Topic :: System :: Hardware
Classifier: License :: OSI Approved :: MIT License
Classifier: Programming Language :: Python :: 3
License-File: LICENSE
Requires-Dist: Adafruit-Blinka
Provides-Extra: optional
